{
  "books": [
    {"num":1,  "code":"GEN", "fr":"Genèse",           "en":"Genesis",          "t":"OT", "ch":[31,25,24,26,32,22,24,22,29,32,32,20,18,24,21,16,27,33,38,18,34,24,20,67,34,35,46,22,35,43,55,32,20,31,29,43,36,30,23,23,57,38,34,34,28,34,31,22,33,26]},
    {"num":2,  "code":"EXO", "fr":"Exode",            "en":"Exodus",           "t":"OT", "ch":[22,25,22,31,23,30,25,32,35,29,10,51,22,31,27,36,16,27,25,26,36,31,33,18,40,37,21,43,46,38,18,35,23,35,35,38,29,31,43,38]},
    {"num":3,  "code":"LEV", "fr":"Lévitique",        "en":"Leviticus",        "t":"OT", "ch":[17,16,17,35,26,23,38,36,24,20,47,8,59,57,33,34,16,30,24,16,30,34,26,25,12,20,26]},
    {"num":4,  "code":"NUM", "fr":"Nombres",          "en":"Numbers",          "t":"OT", "ch":[54,34,51,49,31,27,89,26,23,36,31,16,23,21,13,23,24,17,40,13,27,33,34,53,46,12,28,18,13,10,21,24,17,22,28,36]},
    {"num":5,  "code":"DEU", "fr":"Deutéronome",      "en":"Deuteronomy",      "t":"OT", "ch":[46,37,29,49,33,25,26,20,29,22,32,32,18,29,23,22,20,22,21,20,23,30,25,22,19,19,26,68,29,20,30,52,29,12]},
    {"num":6,  "code":"JOS", "fr":"Josué",            "en":"Joshua",           "t":"OT", "ch":[18,24,17,24,15,27,26,35,27,43,23,24,33,15,63,10,18,28,51,9,45,34,16,33]},
    {"num":7,  "code":"JDG", "fr":"Juges",            "en":"Judges",           "t":"OT", "ch":[36,23,31,24,31,40,25,35,57,18,40,15,25,20,20,31,13,31,30,48,25]},
    {"num":8,  "code":"RUT", "fr":"Ruth",             "en":"Ruth",             "t":"OT", "ch":[22,23,18,22]},
    {"num":9,  "code":"1SA", "fr":"1 Samuel",         "en":"1 Samuel",         "t":"OT", "ch":[28,36,21,22,12,21,17,22,27,27,15,25,23,52,35,23,58,30,24,42,15,23,29,22,44,25,12,25,11,31,13]},
    {"num":10, "code":"2SA", "fr":"2 Samuel",         "en":"2 Samuel",         "t":"OT", "ch":[27,32,39,12,25,23,29,18,13,19,27,31,39,33,37,23,29,33,43,26,22,51,39,25]},
    {"num":11, "code":"1KI", "fr":"1 Rois",           "en":"1 Kings",          "t":"OT", "ch":[53,46,28,34,18,38,51,66,28,29,43,33,34,31,34,34,24,46,21,43,29,53]},
    {"num":12, "code":"2KI", "fr":"2 Rois",           "en":"2 Kings",          "t":"OT", "ch":[18,25,27,44,27,33,20,29,37,36,21,21,25,29,38,20,41,37,37,21,26,20,37,20,30]},
    {"num":13, "code":"1CH", "fr":"1 Chroniques",     "en":"1 Chronicles",     "t":"OT", "ch":[54,55,24,43,26,81,40,40,44,14,47,40,14,17,29,43,27,17,19,8,30,19,32,31,31,32,34,21,30]},
    {"num":14, "code":"2CH", "fr":"2 Chroniques",     "en":"2 Chronicles",     "t":"OT", "ch":[17,18,17,22,14,42,22,18,31,19,23,16,22,15,19,14,19,34,11,37,20,12,21,27,28,23,9,27,36,27,21,33,25,33,27,23]},
    {"num":15, "code":"EZR", "fr":"Esdras",           "en":"Ezra",             "t":"OT", "ch":[11,70,13,24,17,22,28,36,15,44]},
    {"num":16, "code":"NEH", "fr":"Néhémie",          "en":"Nehemiah",         "t":"OT", "ch":[11,20,32,23,19,19,73,18,38,39,36,47,31]},
    {"num":17, "code":"EST", "fr":"Esther",           "en":"Esther",           "t":"OT", "ch":[22,23,15,17,14,14,10,17,32,3]},
    {"num":18, "code":"JOB", "fr":"Job",              "en":"Job",              "t":"OT", "ch":[22,13,26,21,27,30,21,22,35,22,20,25,28,22,35,22,16,21,29,29,34,30,17,25,6,14,23,28,25,31,40,22,33,37,16,33,24,41,30,24,34,17]},
    {"num":19, "code":"PSA", "fr":"Psaumes",          "en":"Psalms",           "t":"OT", "ch":[6,12,8,8,12,10,17,9,20,18,7,8,6,7,5,11,15,50,14,9,13,31,6,10,22,12,14,9,11,12,24,11,22,22,28,12,40,22,13,17,13,11,5,20,28,22,35,22,46,28,14,9,31,22,31,15,19,29,28,7,19,29,28,21,33,17,10,10,11,18,16,13,14,23,27,11,34,23,15,17,14,21,18,30,15,20,24,32,27,26,14,27,17,21,23,12,29,11,35,17,31,31,10,34,26,44,13,13,5,20]},
    {"num":20, "code":"PRO", "fr":"Proverbes",        "en":"Proverbs",         "t":"OT", "ch":[33,22,35,27,23,35,27,36,18,32,31,28,25,35,33,33,28,24,29,30,31,29,35,34,28,28,27,28,27,33,31]},
    {"num":21, "code":"ECC", "fr":"Ecclésiaste",      "en":"Ecclesiastes",     "t":"OT", "ch":[18,26,22,16,20,12,29,17,18,20,10,14]},
    {"num":22, "code":"SNG", "fr":"Cantique",         "en":"Song of Solomon",  "t":"OT", "ch":[17,17,11,16,16,13,13,14]},
    {"num":23, "code":"ISA", "fr":"Ésaïe",            "en":"Isaiah",           "t":"OT", "ch":[31,22,26,6,30,13,25,22,21,34,16,6,22,32,9,14,14,7,25,6,17,25,18,23,12,21,13,29,24,33,9,20,24,17,10,22,38,22,8,31,29,25,28,28,25,13,15,22,26,11,23,15,12,17,13,12,21,14,21,22,11,12,19,12,25,24]},
    {"num":24, "code":"JER", "fr":"Jérémie",          "en":"Jeremiah",         "t":"OT", "ch":[19,37,25,31,31,30,34,22,26,25,23,17,27,22,21,21,27,23,15,18,14,30,40,10,38,24,22,17,32,24,40,44,26,22,19,32,20,28,18,16,18,22,13,30,5,28,7,47,39,46,64,34]},
    {"num":25, "code":"LAM", "fr":"Lamentations",     "en":"Lamentations",     "t":"OT", "ch":[22,22,66,22,22]},
    {"num":26, "code":"EZK", "fr":"Ézéchiel",         "en":"Ezekiel",          "t":"OT", "ch":[28,10,27,17,17,14,27,18,11,22,25,28,23,23,8,63,24,32,14,49,32,31,49,27,17,21,36,26,21,26,18,32,33,31,15,38,28,23,29,49,26,20,27,31,25,24,23,35]},
    {"num":27, "code":"DAN", "fr":"Daniel",           "en":"Daniel",           "t":"OT", "ch":[21,49,30,37,31,28,28,27,27,21,45,13]},
    {"num":28, "code":"HOS", "fr":"Osée",             "en":"Hosea",            "t":"OT", "ch":[11,23,5,19,15,11,16,14,17,15,12,14,16,9]},
    {"num":29, "code":"JOL", "fr":"Joël",             "en":"Joel",             "t":"OT", "ch":[20,32,21]},
    {"num":30, "code":"AMO", "fr":"Amos",             "en":"Amos",             "t":"OT", "ch":[15,16,15,13,27,14,17,14,15]},
    {"num":31, "code":"OBA", "fr":"Abdias",           "en":"Obadiah",          "t":"OT", "ch":[21]},
    {"num":32, "code":"JON", "fr":"Jonas",            "en":"Jonah",            "t":"OT", "ch":[17,10,10,11]},
    {"num":33, "code":"MIC", "fr":"Michée",           "en":"Micah",            "t":"OT", "ch":[16,13,12,13,15,16,20]},
    {"num":34, "code":"NAH", "fr":"Nahoum",           "en":"Nahum",            "t":"OT", "ch":[15,13,19]},
    {"num":35, "code":"HAB", "fr":"Habacuc",          "en":"Habakkuk",         "t":"OT", "ch":[17,20,19]},
    {"num":36, "code":"ZEP", "fr":"Sophonie",         "en":"Zephaniah",        "t":"OT", "ch":[18,15,20]},
    {"num":37, "code":"HAG", "fr":"Aggée",            "en":"Haggai",           "t":"OT", "ch":[15,23]},
    {"num":38, "code":"ZEC", "fr":"Zacharie",         "en":"Zechariah",        "t":"OT", "ch":[21,13,10,14,11,15,14,23,17,12,17,14,9,21]},
    {"num":39, "code":"MAL", "fr":"Malachie",         "en":"Malachi",          "t":"OT", "ch":[14,17,18,6]},
    {"num":40, "code":"MAT", "fr":"Matthieu",         "en":"Matthew",          "t":"NT", "ch":[25,23,17,25,48,34,29,34,38,42,30,50,58,36,39,28,27,35,30,34,46,46,39,51,46,75,66,20]},
    {"num":41, "code":"MRK", "fr":"Marc",             "en":"Mark",             "t":"NT", "ch":[45,28,35,41,43,56,37,38,50,52,33,44,37,72,47,20]},
    {"num":42, "code":"LUK", "fr":"Luc",              "en":"Luke",             "t":"NT", "ch":[80,52,38,44,39,49,50,56,62,42,54,59,35,35,32,31,37,43,48,47,38,71,56,53]},
    {"num":43, "code":"JHN", "fr":"Jean",             "en":"John",             "t":"NT", "ch":[51,25,36,54,47,71,53,59,41,42,57,50,38,31,27,33,26,40,42,31,25]},
    {"num":44, "code":"ACT", "fr":"Actes",            "en":"Acts",             "t":"NT", "ch":[26,47,26,37,42,15,60,40,43,48,30,25,52,28,41,40,34,28,41,38,40,30,35,27,27,32,44,31]},
    {"num":45, "code":"ROM", "fr":"Romains",          "en":"Romans",           "t":"NT", "ch":[32,29,31,25,21,23,25,39,33,21,36,21,14,26,33,25]},
    {"num":46, "code":"1CO", "fr":"1 Corinthiens",    "en":"1 Corinthians",    "t":"NT", "ch":[31,16,23,21,13,20,40,13,27,33,34,31,13,40,58,24]},
    {"num":47, "code":"2CO", "fr":"2 Corinthiens",    "en":"2 Corinthians",    "t":"NT", "ch":[24,17,18,18,21,18,16,24,15,18,33,21,14]},
    {"num":48, "code":"GAL", "fr":"Galates",          "en":"Galatians",        "t":"NT", "ch":[24,21,29,31,26,18]},
    {"num":49, "code":"EPH", "fr":"Éphésiens",        "en":"Ephesians",        "t":"NT", "ch":[23,22,21,28,20,32]},
    {"num":50, "code":"PHP", "fr":"Philippiens",      "en":"Philippians",      "t":"NT", "ch":[30,30,21,23]},
    {"num":51, "code":"COL", "fr":"Colossiens",       "en":"Colossians",       "t":"NT", "ch":[29,23,25,18]},
    {"num":52, "code":"1TH", "fr":"1 Thessaloniciens","en":"1 Thessalonians",  "t":"NT", "ch":[10,20,13,18,28]},
    {"num":53, "code":"2TH", "fr":"2 Thessaloniciens","en":"2 Thessalonians",  "t":"NT", "ch":[12,17,18]},
    {"num":54, "code":"1TI", "fr":"1 Timothée",       "en":"1 Timothy",        "t":"NT", "ch":[20,15,16,16,25,21]},
    {"num":55, "code":"2TI", "fr":"2 Timothée",       "en":"2 Timothy",        "t":"NT", "ch":[18,26,17,22]},
    {"num":56, "code":"TIT", "fr":"Tite",             "en":"Titus",            "t":"NT", "ch":[16,15,15]},
    {"num":57, "code":"PHM", "fr":"Philémon",         "en":"Philemon",         "t":"NT", "ch":[25]},
    {"num":58, "code":"HEB", "fr":"Hébreux",          "en":"Hebrews",          "t":"NT", "ch":[14,18,19,16,14,20,28,13,28,39,40,29,25]},
    {"num":59, "code":"JAS", "fr":"Jacques",          "en":"James",            "t":"NT", "ch":[27,26,18,17,20]},
    {"num":60, "code":"1PE", "fr":"1 Pierre",         "en":"1 Peter",          "t":"NT", "ch":[25,25,22,19,14]},
    {"num":61, "code":"2PE", "fr":"2 Pierre",         "en":"2 Peter",          "t":"NT", "ch":[21,22,18]},
    {"num":62, "code":"1JN", "fr":"1 Jean",           "en":"1 John",           "t":"NT", "ch":[10,29,24,21,21]},
    {"num":63, "code":"2JN", "fr":"2 Jean",           "en":"2 John",           "t":"NT", "ch":[13]},
    {"num":64, "code":"3JN", "fr":"3 Jean",           "en":"3 John",           "t":"NT", "ch":[15]},
    {"num":65, "code":"JUD", "fr":"Jude",             "en":"Jude",             "t":"NT", "ch":[25]},
    {"num":66, "code":"REV", "fr":"Apocalypse",       "en":"Revelation",       "t":"NT", "ch":[20,29,22,11,14,17,17,13,21,11,19,17,18,20,8,21,18,24,21,15,27,21]}
  ]
}
